crosshatch/__init__.py
crosshatch/__main__.py
crosshatch/commands.py
crosshatch/const.py
crosshatch/highlighter.py
crosshatch/repl.py
crosshatch-1.0.0.dist-info/METADATA
crosshatch-1.0.0.dist-info/WHEEL
crosshatch-1.0.0.dist-info/entry_points.txt
crosshatch-1.0.0.dist-info/RECORD
