Metadata-Version: 2.1
Name: crosshatch
Version: 1.0.0
Summary: A pretty REPL for Vyxal.
Home-page: https://github.com/Vyxal/Crosshatch
Author: Ginger
Author-email: 75683114+GingerIndustries@users.noreply.github.com
Requires-Python: >=3.10,<3.11
Classifier: Programming Language :: Python :: 3
Classifier: Programming Language :: Python :: 3.10
Requires-Dist: rich (>=13.2.0,<14.0.0)
Requires-Dist: vyxal (>=2.18,<3.0)
Project-URL: Repository, https://github.com/Vyxal/Crosshatch
